{
  "generated_at": "2026-06-04T23:59:26Z",
  "p_threshold": 0.15,
  "n_cv_windows": 12,
  "universe_size": 160,
  "optimal_params": {
    "dist_t": -0.15,
    "dfv_lift": 2.5,
    "quality_t": 0.2,
    "trend_t": 0.0
  },
  "buy_weights": {
    "f": 50,
    "fdfv3": 50
  },
  "buy_wb_penalty": -15,
  "fundamental_boost_max": 15,
  "sell_weights": {
    "near_high": 100
  },
  "signal_results_252d": {
    "f": {
      "mean_sep": 0.2414,
      "std": 0.2789,
      "ci_lo": 0.1118,
      "ci_hi": 0.4218,
      "p_value": 0.0152,
      "significant": true,
      "n_wins": 10,
      "n_windows": 12,
      "win_rate": 0.8333
    },
    "fdfv3": {
      "mean_sep": 0.2439,
      "std": 0.2792,
      "ci_lo": 0.1007,
      "ci_hi": 0.3922,
      "p_value": 0.0145,
      "significant": true,
      "n_wins": 9,
      "n_windows": 12,
      "win_rate": 0.75
    },
    "pfd": {
      "mean_sep": 0.0474,
      "std": 0.1044,
      "ci_lo": -0.0146,
      "ci_hi": 0.11,
      "p_value": 0.1597,
      "significant": false,
      "n_wins": 6,
      "n_windows": 12,
      "win_rate": 0.5
    },
    "triple": {
      "mean_sep": 0.0712,
      "std": 0.1576,
      "ci_lo": -0.0206,
      "ci_hi": 0.1517,
      "p_value": 0.162,
      "significant": false,
      "n_wins": 7,
      "n_windows": 12,
      "win_rate": 0.5833
    },
    "dfv3": {
      "mean_sep": -0.0011,
      "std": 0.021,
      "ci_lo": -0.0117,
      "ci_hi": 0.0101,
      "p_value": 0.8627,
      "significant": false,
      "n_wins": 6,
      "n_windows": 12,
      "win_rate": 0.5
    },
    "dfv1": {
      "mean_sep": -0.0144,
      "std": 0.102,
      "ci_lo": -0.0711,
      "ci_hi": 0.0477,
      "p_value": 0.65,
      "significant": false,
      "n_wins": 5,
      "n_windows": 12,
      "win_rate": 0.4167
    },
    "near_high": {
      "mean_sep": -0.0807,
      "std": 0.0808,
      "ci_lo": -0.1361,
      "ci_hi": -0.042,
      "p_value": 0.007,
      "significant": false,
      "n_wins": 1,
      "n_windows": 12,
      "win_rate": 0.0833
    },
    "wb": {
      "mean_sep": 0.027,
      "std": 0.1544,
      "ci_lo": -0.0748,
      "ci_hi": 0.1089,
      "p_value": 0.573,
      "significant": false,
      "n_wins": 6,
      "n_windows": 12,
      "win_rate": 0.5
    },
    "rbear": {
      "mean_sep": 0.0965,
      "std": 0.1051,
      "ci_lo": 0.0335,
      "ci_hi": 0.1508,
      "p_value": 0.0111,
      "significant": true,
      "n_wins": 8,
      "n_windows": 12,
      "win_rate": 0.6667
    },
    "wb_div": {},
    "mom20": {
      "mean_sep": 0.0712,
      "std": 0.1576,
      "ci_lo": -0.0214,
      "ci_hi": 0.1519,
      "p_value": 0.162,
      "significant": false,
      "n_wins": 7,
      "n_windows": 12,
      "win_rate": 0.5833
    },
    "mom30": {
      "mean_sep": 0.1363,
      "std": 0.1995,
      "ci_lo": 0.0242,
      "ci_hi": 0.2449,
      "p_value": 0.0446,
      "significant": true,
      "n_wins": 8,
      "n_windows": 12,
      "win_rate": 0.6667
    },
    "mfbear": {
      "mean_sep": 0.0673,
      "std": 0.0671,
      "ci_lo": 0.0305,
      "ci_hi": 0.1024,
      "p_value": 0.0067,
      "significant": true,
      "n_wins": 8,
      "n_windows": 12,
      "win_rate": 0.6667
    },
    "bred": {
      "mean_sep": 0.0881,
      "std": 0.0935,
      "ci_lo": 0.035,
      "ci_hi": 0.1403,
      "p_value": 0.0097,
      "significant": true,
      "n_wins": 8,
      "n_windows": 12,
      "win_rate": 0.6667
    },
    "qual_det": {
      "mean_sep": -0.0105,
      "std": 0.0598,
      "ci_lo": -0.0439,
      "ci_hi": 0.0192,
      "p_value": 0.5706,
      "significant": false,
      "n_wins": 5,
      "n_windows": 12,
      "win_rate": 0.4167
    },
    "rvbear": {
      "mean_sep": 0.0643,
      "std": 0.0726,
      "ci_lo": 0.0267,
      "ci_hi": 0.1084,
      "p_value": 0.0135,
      "significant": true,
      "n_wins": 8,
      "n_windows": 12,
      "win_rate": 0.6667
    }
  },
  "consistency": {
    "f": 4,
    "fdfv3": 4,
    "pfd": 2,
    "triple": 3,
    "dfv3": 0,
    "dfv1": 0,
    "near_high": 4,
    "wb": 0,
    "rbear": 0,
    "wb_div": 0,
    "mom20": 0,
    "mom30": 0,
    "mfbear": 0,
    "bred": 0,
    "qual_det": 0,
    "rvbear": 0
  },
  "sell_signal_ranking": [
    {
      "signal": "near_high",
      "name": "Near 252d high",
      "mean_sep_252d": -8.07,
      "p_value": 0.007,
      "consistency": 4,
      "validated": true,
      "weight": 100
    },
    {
      "signal": "wb",
      "name": "Banker Weak",
      "mean_sep_252d": 2.7,
      "p_value": 0.573,
      "consistency": 0,
      "validated": false,
      "weight": 0
    },
    {
      "signal": "rbear",
      "name": "RSI14 bearish div",
      "mean_sep_252d": 9.65,
      "p_value": 0.0111,
      "consistency": 0,
      "validated": false,
      "weight": 0
    },
    {
      "signal": "wb_div",
      "name": "WB + div combo",
      "mean_sep_252d": null,
      "p_value": null,
      "consistency": 0,
      "validated": false,
      "weight": 0
    },
    {
      "signal": "mom20",
      "name": "Momentum exhaust 20%",
      "mean_sep_252d": 7.12,
      "p_value": 0.162,
      "consistency": 0,
      "validated": false,
      "weight": 0
    },
    {
      "signal": "mom30",
      "name": "Momentum exhaust 30%",
      "mean_sep_252d": 13.63,
      "p_value": 0.0446,
      "consistency": 0,
      "validated": false,
      "weight": 0
    },
    {
      "signal": "mfbear",
      "name": "MFI bearish div",
      "mean_sep_252d": 6.73,
      "p_value": 0.0067,
      "consistency": 0,
      "validated": false,
      "weight": 0
    },
    {
      "signal": "bred",
      "name": "BRED (2+ components)",
      "mean_sep_252d": 8.81,
      "p_value": 0.0097,
      "consistency": 0,
      "validated": false,
      "weight": 0
    },
    {
      "signal": "qual_det",
      "name": "Quality deterioration",
      "mean_sep_252d": -1.05,
      "p_value": 0.5706,
      "consistency": 0,
      "validated": false,
      "weight": 0
    },
    {
      "signal": "rvbear",
      "name": "RVI bearish div proxy",
      "mean_sep_252d": 6.43,
      "p_value": 0.0135,
      "consistency": 0,
      "validated": false,
      "weight": 0
    }
  ]
}