{
  "generated_at": "2026-07-01T21:32:36Z",
  "p_threshold": 0.15,
  "n_cv_windows": 12,
  "universe_size": 159,
  "optimal_params": {
    "dist_t": -0.15,
    "dfv_lift": 2.5,
    "quality_t": 0.2,
    "trend_t": 0.0
  },
  "buy_weights": {
    "f": 41,
    "fdfv3": 43,
    "triple": 16
  },
  "buy_wb_penalty": -15,
  "fundamental_boost_max": 15,
  "sell_weights": {
    "near_high": 100
  },
  "signal_results_252d": {
    "f": {
      "mean_sep": 0.2347,
      "std": 0.2786,
      "ci_lo": 0.1027,
      "ci_hi": 0.4146,
      "p_value": 0.0174,
      "significant": true,
      "n_wins": 10,
      "n_windows": 12,
      "win_rate": 0.8333
    },
    "fdfv3": {
      "mean_sep": 0.2497,
      "std": 0.2792,
      "ci_lo": 0.108,
      "ci_hi": 0.3979,
      "p_value": 0.0128,
      "significant": true,
      "n_wins": 9,
      "n_windows": 12,
      "win_rate": 0.75
    },
    "pfd": {
      "mean_sep": 0.041,
      "std": 0.1127,
      "ci_lo": -0.0287,
      "ci_hi": 0.106,
      "p_value": 0.2533,
      "significant": false,
      "n_wins": 6,
      "n_windows": 12,
      "win_rate": 0.5
    },
    "triple": {
      "mean_sep": 0.0907,
      "std": 0.1012,
      "ci_lo": 0.0345,
      "ci_hi": 0.1485,
      "p_value": 0.0127,
      "significant": true,
      "n_wins": 9,
      "n_windows": 12,
      "win_rate": 0.75
    },
    "dfv3": {
      "mean_sep": 0.0077,
      "std": 0.0374,
      "ci_lo": -0.0117,
      "ci_hi": 0.0298,
      "p_value": 0.5062,
      "significant": false,
      "n_wins": 6,
      "n_windows": 12,
      "win_rate": 0.5
    },
    "dfv1": {
      "mean_sep": -0.0188,
      "std": 0.0918,
      "ci_lo": -0.0763,
      "ci_hi": 0.0316,
      "p_value": 0.5121,
      "significant": false,
      "n_wins": 6,
      "n_windows": 12,
      "win_rate": 0.5
    },
    "near_high": {
      "mean_sep": -0.0876,
      "std": 0.0848,
      "ci_lo": -0.1466,
      "ci_hi": -0.046,
      "p_value": 0.0057,
      "significant": false,
      "n_wins": 0,
      "n_windows": 12,
      "win_rate": 0.0
    },
    "wb": {
      "mean_sep": 0.0382,
      "std": 0.1126,
      "ci_lo": -0.0268,
      "ci_hi": 0.1016,
      "p_value": 0.285,
      "significant": false,
      "n_wins": 7,
      "n_windows": 12,
      "win_rate": 0.5833
    },
    "rbear": {
      "mean_sep": 0.1039,
      "std": 0.1135,
      "ci_lo": 0.0348,
      "ci_hi": 0.1615,
      "p_value": 0.0113,
      "significant": true,
      "n_wins": 8,
      "n_windows": 12,
      "win_rate": 0.6667
    },
    "wb_div": {},
    "mom20": {
      "mean_sep": 0.0907,
      "std": 0.1012,
      "ci_lo": 0.0373,
      "ci_hi": 0.1431,
      "p_value": 0.0127,
      "significant": true,
      "n_wins": 9,
      "n_windows": 12,
      "win_rate": 0.75
    },
    "mom30": {
      "mean_sep": 0.1437,
      "std": 0.1611,
      "ci_lo": 0.0502,
      "ci_hi": 0.2274,
      "p_value": 0.013,
      "significant": true,
      "n_wins": 9,
      "n_windows": 12,
      "win_rate": 0.75
    },
    "mfbear": {
      "mean_sep": 0.0778,
      "std": 0.075,
      "ci_lo": 0.0391,
      "ci_hi": 0.1136,
      "p_value": 0.0055,
      "significant": true,
      "n_wins": 9,
      "n_windows": 12,
      "win_rate": 0.75
    },
    "bred": {
      "mean_sep": 0.0957,
      "std": 0.098,
      "ci_lo": 0.04,
      "ci_hi": 0.1503,
      "p_value": 0.0079,
      "significant": true,
      "n_wins": 8,
      "n_windows": 12,
      "win_rate": 0.6667
    },
    "qual_det": {
      "mean_sep": -0.018,
      "std": 0.0756,
      "ci_lo": -0.0614,
      "ci_hi": 0.02,
      "p_value": 0.4466,
      "significant": false,
      "n_wins": 4,
      "n_windows": 12,
      "win_rate": 0.3333
    },
    "rvbear": {
      "mean_sep": 0.0659,
      "std": 0.0643,
      "ci_lo": 0.0343,
      "ci_hi": 0.1024,
      "p_value": 0.0059,
      "significant": true,
      "n_wins": 9,
      "n_windows": 12,
      "win_rate": 0.75
    }
  },
  "consistency": {
    "f": 4,
    "fdfv3": 4,
    "pfd": 2,
    "triple": 4,
    "dfv3": 0,
    "dfv1": 0,
    "near_high": 4,
    "wb": 0,
    "rbear": 0,
    "wb_div": 0,
    "mom20": 0,
    "mom30": 0,
    "mfbear": 0,
    "bred": 0,
    "qual_det": 0,
    "rvbear": 0
  },
  "sell_signal_ranking": [
    {
      "signal": "near_high",
      "name": "Near 252d high",
      "mean_sep_252d": -8.76,
      "p_value": 0.0057,
      "consistency": 4,
      "validated": true,
      "weight": 100
    },
    {
      "signal": "wb",
      "name": "Banker Weak",
      "mean_sep_252d": 3.82,
      "p_value": 0.285,
      "consistency": 0,
      "validated": false,
      "weight": 0
    },
    {
      "signal": "rbear",
      "name": "RSI14 bearish div",
      "mean_sep_252d": 10.39,
      "p_value": 0.0113,
      "consistency": 0,
      "validated": false,
      "weight": 0
    },
    {
      "signal": "wb_div",
      "name": "WB + div combo",
      "mean_sep_252d": null,
      "p_value": null,
      "consistency": 0,
      "validated": false,
      "weight": 0
    },
    {
      "signal": "mom20",
      "name": "Momentum exhaust 20%",
      "mean_sep_252d": 9.07,
      "p_value": 0.0127,
      "consistency": 0,
      "validated": false,
      "weight": 0
    },
    {
      "signal": "mom30",
      "name": "Momentum exhaust 30%",
      "mean_sep_252d": 14.37,
      "p_value": 0.013,
      "consistency": 0,
      "validated": false,
      "weight": 0
    },
    {
      "signal": "mfbear",
      "name": "MFI bearish div",
      "mean_sep_252d": 7.78,
      "p_value": 0.0055,
      "consistency": 0,
      "validated": false,
      "weight": 0
    },
    {
      "signal": "bred",
      "name": "BRED (2+ components)",
      "mean_sep_252d": 9.57,
      "p_value": 0.0079,
      "consistency": 0,
      "validated": false,
      "weight": 0
    },
    {
      "signal": "qual_det",
      "name": "Quality deterioration",
      "mean_sep_252d": -1.8,
      "p_value": 0.4466,
      "consistency": 0,
      "validated": false,
      "weight": 0
    },
    {
      "signal": "rvbear",
      "name": "RVI bearish div proxy",
      "mean_sep_252d": 6.59,
      "p_value": 0.0059,
      "consistency": 0,
      "validated": false,
      "weight": 0
    }
  ]
}